Workbook

Sheet Calculadora
A1: LR MAKER LAB · G-CODE 3D
A2: Calculadora de pedido
A3: Custo real, hora de máquina, piso, preço sugerido e margem. Faça a conta antes de responder qualquer orçamento.
A5: Como ler as cores: | B5: Você preenche | C5: Calculado, não mexa | D5: Vem de outra aba
A7: CONFIGURAÇÃO · preencha uma vez com os seus números
A8: Preço do filamento (R$ por kg) | D8: 120 | E8: Hipótese: preço médio de um rolo de 1 kg. Troque pelo que você paga.
A9: Perda e falhas (sobre o filamento) | D9: 0.15 | E9: Mesmo valor usado nos manuais: 15% para purga, suporte e peça perdida.
A10: Potência média da impressora (W) | D10: 150 | E10: Hipótese para impressora de mesa aquecida. Confira na etiqueta da fonte.
A11: Tarifa de energia (R$ por kWh) | D11: 0.95 | E11: Hipótese. Veja o valor na sua conta de luz, com impostos.
A12: Piso por hora de máquina (R$) | D12: 15 | E12: Regra do G-Code 3D: nenhum pedido abaixo de R$ 15 líquidos por hora de máquina.
A13: Meta de retorno por hora (R$) | D13: 40 | E13: Quanto você quer ganhar por hora de máquina. Define o preço sugerido. Hipótese.
A15: PEDIDOS · uma linha por orçamento
A16: Pedido / cliente | B16: G-Code | C16: Peças | D16: Filamento (g) | E16: Horas de máquina | F16: Extras (R$) embalagem, argola, ímã | G16: Filamento (R$) | H16: Energia (R$) | I16: Custo real (R$) | J16: Piso (R$) custo + h × piso | K16: Preço sugerido (R$) custo + h × meta | L16: Seu preço (R$) | M16: Margem (R$) | N16: Margem (%) | O16: Retorno por hora (R$) | P16: Preço por peça (R$) | Q16: Situação
A17: Exemplo · kit de entrega do corretor | B17: G-08 | C17: 2 | D17: 50 | E17: 2.5 | F17: 6.8 | G17: =IF(E17="","",D17/1000*$D$8*(1+$D$9)) -> 6.9 | H17: =IF(E17="","",E17*$D$10/1000*$D$11) -> 0.35625 | I17: =IF(E17="","",G17+H17+F17) -> 14.05625 | J17: =IF(E17="","",I17+E17*$D$12) -> 51.55625 | K17: =IF(E17="","",I17+E17*$D$13) -> 114.05625 | L17: 90 | M17: =IF(OR(E17="",L17=""),"",L17-I17) -> 75.94375 | N17: =IF(OR(E17="",L17="",L17=0),"",M17/L17) -> 0.84381944 | O17: =IF(OR(E17="",L17="",E17=0),"",M17/E17) -> 30.3775 | P17: =IF(OR(L17="",C17="",C17=0),"",L17/C17) -> 45 | Q17: =IF(OR(E17="",L17=""),"",IF(O17<$D$12,"ABAIXO DO PISO: não feche",IF(O17<$D$13,"Acima do piso, abaixo da meta","Na meta"))) -> Acima do piso, abaixo da meta
G18: =IF(E18="","",D18/1000*$D$8*(1+$D$9)) | H18: =IF(E18="","",E18*$D$10/1000*$D$11) | I18: =IF(E18="","",G18+H18+F18) | J18: =IF(E18="","",I18+E18*$D$12) | K18: =IF(E18="","",I18+E18*$D$13) | M18: =IF(OR(E18="",L18=""),"",L18-I18) | N18: =IF(OR(E18="",L18="",L18=0),"",M18/L18) | O18: =IF(OR(E18="",L18="",E18=0),"",M18/E18) | P18: =IF(OR(L18="",C18="",C18=0),"",L18/C18) | Q18: =IF(OR(E18="",L18=""),"",IF(O18<$D$12,"ABAIXO DO PISO: não feche",IF(O18<$D$13,"Acima do piso, abaixo da meta","Na meta")))
G19: =IF(E19="","",D19/1000*$D$8*(1+$D$9)) | H19: =IF(E19="","",E19*$D$10/1000*$D$11) | I19: =IF(E19="","",G19+H19+F19) | J19: =IF(E19="","",I19+E19*$D$12) | K19: =IF(E19="","",I19+E19*$D$13) | M19: =IF(OR(E19="",L19=""),"",L19-I19) | N19: =IF(OR(E19="",L19="",L19=0),"",M19/L19) | O19: =IF(OR(E19="",L19="",E19=0),"",M19/E19) | P19: =IF(OR(L19="",C19="",C19=0),"",L19/C19) | Q19: =IF(OR(E19="",L19=""),"",IF(O19<$D$12,"ABAIXO DO PISO: não feche",IF(O19<$D$13,"Acima do piso, abaixo da meta","Na meta")))
G20: =IF(E20="","",D20/1000*$D$8*(1+$D$9)) | H20: =IF(E20="","",E20*$D$10/1000*$D$11) | I20: =IF(E20="","",G20+H20+F20) | J20: =IF(E20="","",I20+E20*$D$12) | K20: =IF(E20="","",I20+E20*$D$13) | M20: =IF(OR(E20="",L20=""),"",L20-I20) | N20: =IF(OR(E20="",L20="",L20=0),"",M20/L20) | O20: =IF(OR(E20="",L20="",E20=0),"",M20/E20) | P20: =IF(OR(L20="",C20="",C20=0),"",L20/C20) | Q20: =IF(OR(E20="",L20=""),"",IF(O20<$D$12,"ABAIXO DO PISO: não feche",IF(O20<$D$13,"Acima do piso, abaixo da meta","Na meta")))
G21: =IF(E21="","",D21/1000*$D$8*(1+$D$9)) | H21: =IF(E21="","",E21*$D$10/1000*$D$11) | I21: =IF(E21="","",G21+H21+F21) | J21: =IF(E21="","",I21+E21*$D$12) | K21: =IF(E21="","",I21+E21*$D$13) | M21: =IF(OR(E21="",L21=""),"",L21-I21) | N21: =IF(OR(E21="",L21="",L21=0),"",M21/L21) | O21: =IF(OR(E21="",L21="",E21=0),"",M21/E21) | P21: =IF(OR(L21="",C21="",C21=0),"",L21/C21) | Q21: =IF(OR(E21="",L21=""),"",IF(O21<$D$12,"ABAIXO DO PISO: não feche",IF(O21<$D$13,"Acima do piso, abaixo da meta","Na meta")))
G22: =IF(E22="","",D22/1000*$D$8*(1+$D$9)) | H22: =IF(E22="","",E22*$D$10/1000*$D$11) | I22: =IF(E22="","",G22+H22+F22) | J22: =IF(E22="","",I22+E22*$D$12) | K22: =IF(E22="","",I22+E22*$D$13) | M22: =IF(OR(E22="",L22=""),"",L22-I22) | N22: =IF(OR(E22="",L22="",L22=0),"",M22/L22) | O22: =IF(OR(E22="",L22="",E22=0),"",M22/E22) | P22: =IF(OR(L22="",C22="",C22=0),"",L22/C22) | Q22: =IF(OR(E22="",L22=""),"",IF(O22<$D$12,"ABAIXO DO PISO: não feche",IF(O22<$D$13,"Acima do piso, abaixo da meta","Na meta")))
G23: =IF(E23="","",D23/1000*$D$8*(1+$D$9)) | H23: =IF(E23="","",E23*$D$10/1000*$D$11) | I23: =IF(E23="","",G23+H23+F23) | J23: =IF(E23="","",I23+E23*$D$12) | K23: =IF(E23="","",I23+E23*$D$13) | M23: =IF(OR(E23="",L23=""),"",L23-I23) | N23: =IF(OR(E23="",L23="",L23=0),"",M23/L23) | O23: =IF(OR(E23="",L23="",E23=0),"",M23/E23) | P23: =IF(OR(L23="",C23="",C23=0),"",L23/C23) | Q23: =IF(OR(E23="",L23=""),"",IF(O23<$D$12,"ABAIXO DO PISO: não feche",IF(O23<$D$13,"Acima do piso, abaixo da meta","Na meta")))
G24: =IF(E24="","",D24/1000*$D$8*(1+$D$9)) | H24: =IF(E24="","",E24*$D$10/1000*$D$11) | I24: =IF(E24="","",G24+H24+F24) | J24: =IF(E24="","",I24+E24*$D$12) | K24: =IF(E24="","",I24+E24*$D$13) | M24: =IF(OR(E24="",L24=""),"",L24-I24) | N24: =IF(OR(E24="",L24="",L24=0),"",M24/L24) | O24: =IF(OR(E24="",L24="",E24=0),"",M24/E24) | P24: =IF(OR(L24="",C24="",C24=0),"",L24/C24) | Q24: =IF(OR(E24="",L24=""),"",IF(O24<$D$12,"ABAIXO DO PISO: não feche",IF(O24<$D$13,"Acima do piso, abaixo da meta","Na meta")))
G25: =IF(E25="","",D25/1000*$D$8*(1+$D$9)) | H25: =IF(E25="","",E25*$D$10/1000*$D$11) | I25: =IF(E25="","",G25+H25+F25) | J25: =IF(E25="","",I25+E25*$D$12) | K25: =IF(E25="","",I25+E25*$D$13) | M25: =IF(OR(E25="",L25=""),"",L25-I25) | N25: =IF(OR(E25="",L25="",L25=0),"",M25/L25) | O25: =IF(OR(E25="",L25="",E25=0),"",M25/E25) | P25: =IF(OR(L25="",C25="",C25=0),"",L25/C25) | Q25: =IF(OR(E25="",L25=""),"",IF(O25<$D$12,"ABAIXO DO PISO: não feche",IF(O25<$D$13,"Acima do piso, abaixo da meta","Na meta")))
G26: =IF(E26="","",D26/1000*$D$8*(1+$D$9)) | H26: =IF(E26="","",E26*$D$10/1000*$D$11) | I26: =IF(E26="","",G26+H26+F26) | J26: =IF(E26="","",I26+E26*$D$12) | K26: =IF(E26="","",I26+E26*$D$13) | M26: =IF(OR(E26="",L26=""),"",L26-I26) | N26: =IF(OR(E26="",L26="",L26=0),"",M26/L26) | O26: =IF(OR(E26="",L26="",E26=0),"",M26/E26) | P26: =IF(OR(L26="",C26="",C26=0),"",L26/C26) | Q26: =IF(OR(E26="",L26=""),"",IF(O26<$D$12,"ABAIXO DO PISO: não feche",IF(O26<$D$13,"Acima do piso, abaixo da meta","Na meta")))
G27: =IF(E27="","",D27/1000*$D$8*(1+$D$9)) | H27: =IF(E27="","",E27*$D$10/1000*$D$11) | I27: =IF(E27="","",G27+H27+F27) | J27: =IF(E27="","",I27+E27*$D$12) | K27: =IF(E27="","",I27+E27*$D$13) | M27: =IF(OR(E27="",L27=""),"",L27-I27) | N27: =IF(OR(E27="",L27="",L27=0),"",M27/L27) | O27: =IF(OR(E27="",L27="",E27=0),"",M27/E27) | P27: =IF(OR(L27="",C27="",C27=0),"",L27/C27) | Q27: =IF(OR(E27="",L27=""),"",IF(O27<$D$12,"ABAIXO DO PISO: não feche",IF(O27<$D$13,"Acima do piso, abaixo da meta","Na meta")))
G28: =IF(E28="","",D28/1000*$D$8*(1+$D$9)) | H28: =IF(E28="","",E28*$D$10/1000*$D$11) | I28: =IF(E28="","",G28+H28+F28) | J28: =IF(E28="","",I28+E28*$D$12) | K28: =IF(E28="","",I28+E28*$D$13) | M28: =IF(OR(E28="",L28=""),"",L28-I28) | N28: =IF(OR(E28="",L28="",L28=0),"",M28/L28) | O28: =IF(OR(E28="",L28="",E28=0),"",M28/E28) | P28: =IF(OR(L28="",C28="",C28=0),"",L28/C28) | Q28: =IF(OR(E28="",L28=""),"",IF(O28<$D$12,"ABAIXO DO PISO: não feche",IF(O28<$D$13,"Acima do piso, abaixo da meta","Na meta")))
G29: =IF(E29="","",D29/1000*$D$8*(1+$D$9)) | H29: =IF(E29="","",E29*$D$10/1000*$D$11) | I29: =IF(E29="","",G29+H29+F29) | J29: =IF(E29="","",I29+E29*$D$12) | K29: =IF(E29="","",I29+E29*$D$13) | M29: =IF(OR(E29="",L29=""),"",L29-I29) | N29: =IF(OR(E29="",L29="",L29=0),"",M29/L29) | O29: =IF(OR(E29="",L29="",E29=0),"",M29/E29) | P29: =IF(OR(L29="",C29="",C29=0),"",L29/C29) | Q29: =IF(OR(E29="",L29=""),"",IF(O29<$D$12,"ABAIXO DO PISO: não feche",IF(O29<$D$13,"Acima do piso, abaixo da meta","Na meta")))
... G46: =IF(E46="","",D46/1000*$D$8*(1+$D$9)) | H46: =IF(E46="","",E46*$D$10/1000*$D$11) | I46: =IF(E46="","",G46+H46+F46) | J46: =IF(E46="","",I46+E46*$D$12) | K46: =IF(E46="","",I46+E46*$D$13) | M46: =IF(OR(E46="",L46=""),"",L46-I46) | N46: =IF(OR(E46="",L46="",L46=0),"",M46/L46) | O46: =IF(OR(E46="",L46="",E46=0),"",M46/E46) | P46: =IF(OR(L46="",C46="",C46=0),"",L46/C46) | Q46: =IF(OR(E46="",L46=""),"",IF(O46<$D$12,"ABAIXO DO PISO: não feche",IF(O46<$D$13,"Acima do piso, abaixo da meta","Na meta")))
A48: Como a conta funciona (a mesma dos manuais):
A49: Custo real = filamento com perda + energia + extras. Piso = custo real + horas × R$ 15. Margem = seu preço − custo real. Retorno por hora = margem ÷ horas de máquina.
A50: Horas de máquina: use o tempo do fatiador para o pedido inteiro, contando as mesas cheias. Tempo de arte, mensagem e ida à loja não entra aqui: ele é o motivo de o piso existir.
A51: Todo número desta planilha é hipótese a validar: preço de filamento, energia, tempos e preços mudam com a sua impressora, o seu filamento e a sua região.

Sheet 20 Alvos
A1: LR MAKER LAB · G-CODE 3D
A2: 20 Alvos
A3: Prospecção com status. Preencha no carro, depois de cada visita; à noite, confira a coluna Volto em.
A5: Como ler as cores: | B5: Você preenche | C5: Calculado, não mexa | D5: Vem de outra aba
A7: RESUMO
A8: Alvos listados | C8: =COUNTA(B18:B37) -> 1 | D8: Voltas vencidas ou para hoje | F8: =COUNTIFS(M18:M37,"<="&TODAY(),I18:I37,"<>Fechou",I18:I37,"<>Não agora") -> 0
A9: Visitas feitas | C9: =COUNT(H18:H37) -> 1 | D9: Total proposto (R$) | F9: =SUM(N18:N37) -> 570
A10: Propostas na mão | C10: =COUNTIF(J18:J37,"Sim") -> 1 | D10: Total fechado (R$) | F10: =SUM(O18:O37) -> 0
A11: Fecharam | C11: =COUNTIF(I18:I37,"Fechou") -> 0 | D11: Oportunidades ouvidas | F11: =COUNTA(L18:L37) -> 1
A13: Status: A visitar → Visitado → Amostra deixada → Proposta entregue → Follow-up 48h → 7 dias → final → Fechou ou Não agora. "Proposta na mão" é Sim só quando a proposta impressa ficou com quem decide.
A14: Volto em fica verde-claro quando chega o dia. Oportunidades ouvidas: o que ele pediu que não era o seu produto (seção 11 do manual).
A17: # | B17: Comércio | C17: Bairro | D17: G-Code | E17: Quem decide | F17: WhatsApp ou Instagram | G17: Nota no Google | H17: Data da visita | I17: Status | J17: Proposta na mão? | K17: Objeção, nas palavras exatas | L17: Oportunidade ouvida | M17: Volto em | N17: Valor proposto (R$) | O17: Valor fechado (R$)
A18: 1 | B18: Exemplo · Imobiliária Casa Boa | C18: Centro | D18: G-08 | E18: Marcos, gerente comercial | F18: @casaboa | G18: 4.6 | H18: 46301 | I18: Proposta entregue | J18: Sim | K18: Vou levar para a reunião dos sócios. | L18: Placas de mesa para 6 corretores | M18: 46308 | N18: 570
A19: 2
A20: 3
A21: 4
A22: 5
A23: 6
A24: 7
A25: 8
A26: 9
A27: 10
A28: 11
A29: 12
A30: 13
... A37: 20

Sheet Placar 72h
A1: LR MAKER LAB · G-CODE 3D
A2: Placar 72h
A3: Em 72 horas, você sai da impressora parada para três propostas entregues na mão de um comerciante.
A5: Como ler as cores: | B5: Você preenche | C5: Calculado, não mexa | D5: Vem de outra aba
A7: G-Code escolhido no Seletor | C7: G-08 | D7: Marque Sim só quando o marco estiver 100% feito. Meio feito é Não.
A8: Dia 1 começa em | C8: 46300
A10: Dia | B10: Marco | C10: Feito? | D10: Data | E10: Como saber que está feito
A11: Dia 1 · Preparar | B11: Kit de amostra impresso: dois jogos | C11: Não | D11: =IF($C$8="","",$C$8+0) -> 46300 | E11: As peças da seção 06 do seu manual, conferidas e sem defeito
A12: Dia 1 · Preparar | B12: Embalagem montada, com etiqueta e cartão | C12: Não | D12: =IF($C$8="","",$C$8+0) -> 46300 | E12: Caixa pronta para deixar no balcão
A13: Dia 1 · Preparar | B13: 20 alvos listados na aba 20 Alvos | C13: Não | D13: =IF($C$8="","",$C$8+0) -> 46300 | E13: Coluna Comércio com 20 nomes
A14: Dia 1 · Preparar | B14: Proposta de três níveis impressa | C14: Não | D14: =IF($C$8="","",$C$8+0) -> 46300 | E14: Três cópias, com preço em cada nível
A15: Dia 1 · Preparar | B15: Script de 40 segundos e as seis respostas decorados | C15: Não | D15: =IF($C$8="","",$C$8+0) -> 46300 | E15: Você falou em voz alta sem ler
A16: Dia 2 · Rua | B16: Visitas feitas no horário do manual | C16: Não | D16: =IF($C$8="","",$C$8+1) -> 46301 | E16: Aba 20 Alvos com data de visita
A17: Dia 2 · Rua | B17: Três propostas entregues na mão de quem decide | C17: Não | D17: =IF($C$8="","",$C$8+1) -> 46301 | E17: Aba 20 Alvos com três Sim em Proposta na mão
A18: Dia 2 · Rua | B18: Toda objeção anotada com as palavras exatas | C18: Não | D18: =IF($C$8="","",$C$8+1) -> 46301 | E18: Coluna Objeção preenchida
A19: Dia 3 · Fechar | B19: Follow-up enviado para as três propostas | C19: Não | D19: =IF($C$8="","",$C$8+2) -> 46302 | E19: Status Follow-up 48h enviado
A20: Dia 3 · Fechar | B20: Tudo registrado na aba 20 Alvos | C20: Não | D20: =IF($C$8="","",$C$8+2) -> 46302 | E20: Nenhuma visita só no papel
A21: Dia 3 · Fechar | B21: Oportunidades ouvidas anotadas | C21: Não | D21: =IF($C$8="","",$C$8+2) -> 46302 | E21: Coluna Oportunidade ouvida
A22: Dia 3 · Fechar | B22: Data da próxima leva de visitas marcada | C22: Não | D22: =IF($C$8="","",$C$8+2) -> 46302 | E22: Data escrita na agenda
A24: PLACAR
A25: Marcos feitos | C25: =COUNTIF(C11:C22,"Sim")&" de 12" -> 0 de 12
A26: Dia 1 · Preparar | C26: =COUNTIF(C11:C15,"Sim")&" de 5" -> 0 de 5
A27: Dia 2 · Rua | C27: =COUNTIF(C16:C18,"Sim")&" de 3" -> 0 de 3
A28: Dia 3 · Fechar | C28: =COUNTIF(C19:C22,"Sim")&" de 4" -> 0 de 4
A29: Visitas feitas (da aba 20 Alvos) | C29: ='20 Alvos'!C9 -> 1
A30: Propostas na mão (da aba 20 Alvos) | C30: ='20 Alvos'!C10 -> 1
A32: A missão | C32: =IF(C30>=3,"CUMPRIDA: três propostas na mão","Faltam "&(3-C30)&" propostas na mão") -> Faltam 2 propostas na mão
A34: NÚMERO HONESTO · expectativa, não promessa
A35: Etapa | C35: Referência | D35: Você
A36: Visitas | C36: 10 | D36: ='20 Alvos'!C9 -> 1
A37: Propostas na mão | C37: 3 | D37: ='20 Alvos'!C10 -> 1
A38: Venda | C38: 1 | D38: ='20 Alvos'!F8 -> 0
A40: A venda depende de quem decide do outro lado do balcão, não de você. A missão é sua: três propostas na mão.
A41: Dez visitas e zero vendas não quer dizer que não funciona. Quer dizer que faltam visitas: a segunda leva sai com as objeções de verdade anotadas.
A42: As referências mudam por G-Code: confira o bloco Número honesto da seção 12 do seu manual.
