Workbook

Sheet Comece Aqui
B2: LR MAKER LAB · PAINEL G-CODE 3D
B3: Comece aqui
B4: O manual diz o que fazer. Este painel mostra se você está fazendo.
B7: 1 | C7: Descubra o seu G-Code | K7: Abrir Seletor →
C8: Responda as três perguntas na aba Seletor. Ele indica um G-Code só, e o Painel já recebe o resultado. Os outros nove ficam na biblioteca, para depois da primeira venda.
B10: 2 | C10: Abra o Painel e marque o Dia 1 | K10: Abrir Painel →
C11: O Painel já vem com o seu G-Code. Marque a data do Dia 1 e todas as abas se ajustam: datas, kit, horário de visita e metas.
B13: 3 | C13: Faça a Missão 72h | K13: Abrir Missão 72h →
C14: Dia 1 preparar, Dia 2 rua, Dia 3 fechar. Marque "Sim" em cada ação feita. O Painel mostra sempre a próxima.
B16: 4 | C16: Registre tudo | K16: Abrir Alvos →
C17: Visitas e propostas na aba Alvos, no carro, logo depois de cada visita. Vendas na aba Resultados, com as horas de máquina.
B19: 5 | C19: Expanda no cliente | K19: Abrir Expansão →
C20: Na entrega do primeiro pedido, faça as três perguntas da seção 11 e anote na aba Expansão. Meta: três oportunidades por cliente.
B22: A REGRA DESTE PAINEL
B23: Missão cumprida é três propostas entregues na mão de um comerciante. A venda depende de quem decide do outro lado do balcão, e por isso não é a meta da missão: é o que vem depois de visitas bem feitas e follow-up no prazo.
B26: AS CORES
B27: Aa | C27: Você preenche
B28: Aa | C28: Calculado sozinho, não mexa
B29: Aa | C29: Pronto, ou para hoje
B30: Aa | C30: Atenção: atrasado ou abaixo do piso
B32: AS ABAS
B33: Seletor | D33: as três perguntas que indicam o seu G-Code
B34: Painel | D34: onde você está, a próxima ação e a decisão da semana 2
B35: Missão 72h | D35: as ações dos três dias e da semana 2, com data
B36: Alvos | D36: seus comércios, da lista até a proposta na mão
B37: Calculadora | D37: a conta do preço antes de responder um orçamento
B38: Resultados | D38: cada venda, com lucro e retorno por hora de verdade
B39: Expansão | D39: as oportunidades dentro de quem já comprou
B40: Biblioteca | D40: os dados dos 10 G-Codes que alimentam o Painel

Sheet Seletor
B2: LR MAKER LAB · PAINEL G-CODE 3D
B3: Seletor
B4: Três perguntas. Um G-Code. Responda com a sua realidade de hoje, não com a que você quer ter.
M6: Ir para o Painel →
B7: AS TRÊS PERGUNTAS
B8: 1 | C8: Quanto tempo de máquina livre você tem por dia? | M8: =IF(I8="","← escolha","✓") -> ← escolha
C9: Horas em que a impressora pode rodar pedido seu, contando a noite.
B10: 2 | C10: Você já modela em CAD? | M10: =IF(I10="","← escolha","✓") -> ← escolha
C11: Modelar é desenhar peça com medida, furo e encaixe. Baixar um STL e editar o texto não conta.
B12: 3 | C12: Prefere vender para quem revende ou para quem usa? | M12: =IF(I12="","← escolha","✓") -> ← escolha
C13: Quem revende compra de novo quando vende. Quem usa compra quando precisa.
B15: SEU G-CODE
B16: =IF(I10="Sim, peça com encaixe","G-10",IF(OR(I8="",I10=""),"",IF(I8="Mais de 8h","G-07",IF(I12="","",IF(I8="Menos de 3h",IF(I12="Para quem revende","G-03","G-01"),IF(I12="Para quem revende","G-09","G-04")))))) | E16: =IF(B16="","Faltam "&(3-COUNTA(I8,I10,I12))&" resposta(s). O seu G-Code aparece aqui.",IF(Biblioteca!$F$24=0,"",INDEX(Biblioteca!$C$8:$C$17,Biblioteca!$F$24))) -> Faltam 3 resposta(s). O seu G-Code aparece aqui.
E17: =IF(B16="","",IF(Biblioteca!$F$24=0,"",INDEX(Biblioteca!$D$8:$D$17,Biblioteca!$F$24)))
E18: =IF(B16="","Responda as três perguntas acima. A indicação é uma só, de propósito: quem começa com dois nichos termina a semana sem nenhuma proposta.",IF(Biblioteca!$F$24=0,"",INDEX(Biblioteca!$L$8:$L$17,Biblioteca!$F$24))) -> Responda as três perguntas acima. A indicação é uma só, de propósito: quem começa com dois nichos termina a semana sem nenhuma proposta.
B21: TICKET DO 1º PEDIDO | F21: RETORNO POR HORA | J21: QUANDO VISITAR
B22: =IF(Biblioteca!$F$24=0,"",INDEX(Biblioteca!$E$8:$E$17,Biblioteca!$F$24)) | F22: =IF(Biblioteca!$F$24=0,"",INDEX(Biblioteca!$F$8:$F$17,Biblioteca!$F$24)) | J22: =IF(Biblioteca!$F$24=0,"",INDEX(Biblioteca!$G$8:$G$17,Biblioteca!$F$24))
B24: HOJE À NOITE
B25: =IF(B16="","",IF(B16="G-10","Leia antes a seção 05 do manual: a lista do que nunca imprimir. ","")&"Imprima "&IF(Biblioteca!$F$24=0,"",INDEX(Biblioteca!$H$8:$H$17,Biblioteca!$F$24))&" ("&IF(Biblioteca!$F$24=0,"",INDEX(Biblioteca!$I$8:$I$17,Biblioteca!$F$24))&"). Depois marque o Dia 1 no Painel: comece na "&IF(Biblioteca!$F$24=0,"",INDEX(Biblioteca!$N$8:$N$17,Biblioteca!$F$24))&", para o Dia 2, de rua, cair num dia de visita.")
B27: =IF(B16="","",IF(AND(B16="G-10",OR(I8<>"",I12<>"")),"Com CAD, o G-10 vem primeiro: as outras respostas não mudam o resultado.",IF(B16="G-07","Com mais de 8h de máquina, o G-07 vem primeiro, para quem revende ou para quem usa.",IF(I10="Básico","CAD básico conta como não modelar: o G-10 pede peça com encaixe na primeira tentativa.",""))))
B29: Ir para o Painel → | F29: Abrir a Missão 72h → | I29: O Painel recebe este resultado sozinho.
B31: OS SEIS RESULTADOS POSSÍVEIS
B32: G-01 | C32: Confeitarias | F32: Menos de 3h de máquina, sem CAD, vende para quem usa
B33: G-03 | C33: Pet shops | F33: Menos de 3h de máquina, vende para quem revende
B34: G-04 | C34: Restaurantes, cafés e bares | F34: De 3h a 8h de máquina, sem CAD, vende para quem usa
B35: G-09 | C35: Papelarias e festa | F35: De 3h a 8h de máquina, vende para quem revende
B36: G-07 | C36: Academias | F36: Mais de 8h de máquina por dia
B37: G-10 | C37: Oficinas | F37: Você já modela peça com encaixe em CAD
B39: E os outros quatro? G-02 Nail, G-05 Semijoias, G-06 Lojas de celular e G-08 Imobiliárias ficam na biblioteca. Abra um deles depois da primeira venda, nunca antes. Todo G-Code é venda no balcão: todos pedem visitar o comércio.

Sheet Painel
B2: LR MAKER LAB · PAINEL G-CODE 3D
B3: Painel
B4: Onde você está, o que fazer hoje e o que os seus números dizem.
K6: ← Seletor | M6: Missão 72h →
B7: Seu G-Code (vem do Seletor) | E7: =IF(E8<>"",E8,Biblioteca!$F$23) | J7: Dia 1 da missão | L7: =IF(OR(K7="",E7=""),"← data do Dia 1",IF(ISNUMBER(SEARCH(WEEKDAY(K7+1,2),IF(Biblioteca!$F$22=0,"",INDEX(Biblioteca!$M$8:$M$17,Biblioteca!$F$22)))),"✓ Dia 2 na "&CHOOSE(WEEKDAY(K7+1,2),"segunda","terça","quarta","quinta","sexta","sábado","domingo")&": dia de visita","⚠ Dia 2 cai no(a) "&CHOOSE(WEEKDAY(K7+1,2),"segunda","terça","quarta","quinta","sexta","sábado","domingo")&". Comece na "&IF(Biblioteca!$F$22=0,"",INDEX(Biblioteca!$N$8:$N$17,Biblioteca!$F$22)))) -> ← data do Dia 1
B8: Trocar manualmente (opcional) | J8: ↺ Refazer o Seletor | L8: =IF(E8<>"","troca manual ativa","")
B9: =IF(E7="","Responda as três perguntas na aba Seletor: o seu G-Code aparece aqui sozinho.",IF(Biblioteca!$F$22=0,"",INDEX(Biblioteca!$D$8:$D$17,Biblioteca!$F$22))&" · ticket do 1º pedido "&IF(Biblioteca!$F$22=0,"",INDEX(Biblioteca!$E$8:$E$17,Biblioteca!$F$22))&" · "&IF(Biblioteca!$F$22=0,"",INDEX(Biblioteca!$F$8:$F$17,Biblioteca!$F$22))&" · visite "&IF(Biblioteca!$F$22=0,"",INDEX(Biblioteca!$G$8:$G$17,Biblioteca!$F$22))&" · comece a missão na "&IF(Biblioteca!$F$22=0,"",INDEX(Biblioteca!$N$8:$N$17,Biblioteca!$F$22))) -> Responda as três perguntas na aba Seletor: o seu G-Code aparece aqui sozinho.
B10: DIA DA MISSÃO | E10: MISSÃO 72H CONCLUÍDA | H10: PROPOSTAS NA MÃO | K10: ONDE VOCÊ ESTÁ
B11: =IF(K7="","—",IF(TODAY()<K7,"Começa em "&(K7-TODAY())&" dia(s)",IF(TODAY()-K7+1<=3,"Dia "&(TODAY()-K7+1)&" de 3","Semana 2"))) -> — | E11: =(SUMPRODUCT(('Missão 72h'!$B$8:$B$26<4)*('Missão 72h'!$B$8:$B$26<>"")*('Missão 72h'!$H$8:$H$26="Sim")))/(SUMPRODUCT(('Missão 72h'!$B$8:$B$26<4)*('Missão 72h'!$B$8:$B$26<>"")*1)) -> 0 | H11: =(SUMPRODUCT(((Alvos!$C$13:$C$112=Painel!$E$7)+(Alvos!$C$13:$C$112=""))*(Alvos!$D$13:$D$112<>"")*(Alvos!$K$13:$K$112<>"")))&" de 3" -> 0 de 3 | K11: =IF(E7="","—",IF(AND((SUMPRODUCT(((Alvos!$C$13:$C$112=Painel!$E$7)+(Alvos!$C$13:$C$112=""))*(Alvos!$D$13:$D$112<>"")*(Alvos!$M$13:$M$112="Fechou")))+(SUMPRODUCT(((Resultados!$C$9:$C$108=Painel!$E$7)+(Resultados!$C$9:$C$108=""))*(Resultados!$G$9:$G$108<>"")*1))>=1,(SUMPRODUCT(((Expansão!$D$12:$D$111=Painel!$E$7)+(Expansão!$D$12:$D$111=""))*(Expansão!$C$12:$C$111<>"")*(Expansão!$C$12:$C$111<>"Exemplo · apague")))>=1),"Expandindo",IF((SUMPRODUCT(((Alvos!$C$13:$C$112=Painel!$E$7)+(Alvos!$C$13:$C$112=""))*(Alvos!$D$13:$D$112<>"")*(Alvos!$M$13:$M$112="Fechou")))+(SUMPRODUCT(((Resultados!$C$9:$C$108=Painel!$E$7)+(Resultados!$C$9:$C$108=""))*(Resultados!$G$9:$G$108<>"")*1))>=1,"Vendendo",IF((SUMPRODUCT(((Alvos!$C$13:$C$112=Painel!$E$7)+(Alvos!$C$13:$C$112=""))*(Alvos!$D$13:$D$112<>"")*(Alvos!$K$13:$K$112<>"")))>=3,"Missão cumprida",IF((SUMPRODUCT(((Alvos!$C$13:$C$112=Painel!$E$7)+(Alvos!$C$13:$C$112=""))*(Alvos!$D$13:$D$112<>"")*(Alvos!$K$13:$K$112<>"")))>=1,"Com propostas",IF((SUMPRODUCT(((Alvos!$C$13:$C$112=Painel!$E$7)+(Alvos!$C$13:$C$112=""))*(Alvos!$D$13:$D$112<>"")*(Alvos!$I$13:$I$112<>"")))>=1,"Na rua",IF((SUMPRODUCT(((Alvos!$C$13:$C$112=Painel!$E$7)+(Alvos!$C$13:$C$112=""))*(Alvos!$D$13:$D$112<>"")*1))>=1,"Mapeando","Preparando"))))))) -> —
B12: 72 horas: preparar, rua, fechar | E12: =REPT("■",ROUND(((SUMPRODUCT(('Missão 72h'!$B$8:$B$26<4)*('Missão 72h'!$B$8:$B$26<>"")*('Missão 72h'!$H$8:$H$26="Sim")))/(SUMPRODUCT(('Missão 72h'!$B$8:$B$26<4)*('Missão 72h'!$B$8:$B$26<>"")*1)))*20,0))&REPT("□",20-ROUND(((SUMPRODUCT(('Missão 72h'!$B$8:$B$26<4)*('Missão 72h'!$B$8:$B$26<>"")*('Missão 72h'!$H$8:$H$26="Sim")))/(SUMPRODUCT(('Missão 72h'!$B$8:$B$26<4)*('Missão 72h'!$B$8:$B$26<>"")*1)))*20,0)) -> □□□□□□□□□□□□□□□□□□□□ | H12: a promessa do G-Code 3D | K12: Preparando → Na rua → Propostas → Vendendo → Expandindo
B14: PRÓXIMA AÇÃO
B15: =IF(E7="","Responda as três perguntas na aba Seletor.",IF(K7="","Marque a data do Dia 1 ao lado do G-Code.",IFERROR("Dia "&INDEX('Missão 72h'!$B$8:$B$26,MATCH("Não",'Missão 72h'!$H$8:$H$26,0))&": "&INDEX('Missão 72h'!$D$8:$D$26,MATCH("Não",'Missão 72h'!$H$8:$H$26,0)),"Tudo marcado. Leia a decisão da semana 2 abaixo."))) -> Responda as três perguntas na aba Seletor.
B17: A primeira ação da Missão 72h que ainda está como "Não". Marque "Sim" na aba Missão 72h quando fizer.
B19: FUNIL DO SEU G-CODE | I19: SEU G-CODE EM UMA OLHADA
B20: Etapa | C20: Feito | D20: Meta | E20: Progresso | I20: Nível | J20: =IF(Biblioteca!$F$22=0,"",INDEX(Biblioteca!$D$8:$D$17,Biblioteca!$F$22))
B21: Alvos listados | C21: =SUMPRODUCT(((Alvos!$C$13:$C$112=Painel!$E$7)+(Alvos!$C$13:$C$112=""))*(Alvos!$D$13:$D$112<>"")*1) -> 0 | D21: 20 | E21: =REPT("■",MIN(10,ROUND(C21/D21*10,0)))&REPT("□",10-MIN(10,ROUND(C21/D21*10,0))) -> □□□□□□□□□□ | I21: Ticket do 1º pedido | J21: =IF(Biblioteca!$F$22=0,"",INDEX(Biblioteca!$E$8:$E$17,Biblioteca!$F$22))
B22: Visitados | C22: =SUMPRODUCT(((Alvos!$C$13:$C$112=Painel!$E$7)+(Alvos!$C$13:$C$112=""))*(Alvos!$D$13:$D$112<>"")*(Alvos!$I$13:$I$112<>"")) -> 0 | D22: 10 | E22: =REPT("■",MIN(10,ROUND(C22/D22*10,0)))&REPT("□",10-MIN(10,ROUND(C22/D22*10,0))) -> □□□□□□□□□□ | I22: Retorno por hora | J22: =IF(Biblioteca!$F$22=0,"",INDEX(Biblioteca!$F$8:$F$17,Biblioteca!$F$22))
B23: Amostras deixadas | C23: =SUMPRODUCT(((Alvos!$C$13:$C$112=Painel!$E$7)+(Alvos!$C$13:$C$112=""))*(Alvos!$D$13:$D$112<>"")*(Alvos!$J$13:$J$112="Sim")) -> 0 | D23: 3 | E23: =REPT("■",MIN(10,ROUND(C23/D23*10,0)))&REPT("□",10-MIN(10,ROUND(C23/D23*10,0))) -> □□□□□□□□□□ | I23: Quando visitar | J23: =IF(Biblioteca!$F$22=0,"",INDEX(Biblioteca!$G$8:$G$17,Biblioteca!$F$22))
B24: Propostas na mão | C24: =SUMPRODUCT(((Alvos!$C$13:$C$112=Painel!$E$7)+(Alvos!$C$13:$C$112=""))*(Alvos!$D$13:$D$112<>"")*(Alvos!$K$13:$K$112<>"")) -> 0 | D24: 3 | E24: =REPT("■",MIN(10,ROUND(C24/D24*10,0)))&REPT("□",10-MIN(10,ROUND(C24/D24*10,0))) -> □□□□□□□□□□ | I24: Kit de amostra | J24: =IF(Biblioteca!$F$22=0,"",INDEX(Biblioteca!$H$8:$H$17,Biblioteca!$F$22))
B25: Fecharam | C25: =SUMPRODUCT(((Alvos!$C$13:$C$112=Painel!$E$7)+(Alvos!$C$13:$C$112=""))*(Alvos!$D$13:$D$112<>"")*(Alvos!$M$13:$M$112="Fechou")) -> 0 | D25: 1 | E25: =REPT("■",MIN(10,ROUND(C25/D25*10,0)))&REPT("□",10-MIN(10,ROUND(C25/D25*10,0))) -> □□□□□□□□□□ | I25: Número honesto | J25: =IF(Biblioteca!$F$22=0,"",INDEX(Biblioteca!$J$8:$J$17,Biblioteca!$F$22))
B26: Referência de Fecharam: 1 venda a cada 10 visitas é o número honesto dos manuais. É expectativa, não promessa: a venda depende de quem decide do outro lado do balcão. | I26: Manual | J26: =IF(Biblioteca!$F$22=0,"",INDEX(Biblioteca!$B$8:$B$17,Biblioteca!$F$22)&" · leia a Cola de balcão antes de entrar")
B28: RESULTADOS · da aba Resultados
B29: VENDAS | E29: FATURAMENTO | H29: LUCRO | K29: LUCRO POR HORA DE MÁQUINA
B30: =SUMPRODUCT(((Resultados!$C$9:$C$108=Painel!$E$7)+(Resultados!$C$9:$C$108=""))*(Resultados!$G$9:$G$108<>"")*1) -> 0 | E30: =SUMPRODUCT(((Resultados!$C$9:$C$108=Painel!$E$7)+(Resultados!$C$9:$C$108=""))*(Resultados!$G$9:$G$108<>"")*IFERROR(Resultados!$G$9:$G$108*1,0)) -> 0 | H30: =SUMPRODUCT(((Resultados!$C$9:$C$108=Painel!$E$7)+(Resultados!$C$9:$C$108=""))*(Resultados!$G$9:$G$108<>"")*IFERROR(Resultados!$L$9:$L$108*1,0)) -> 0 | K30: =IF((SUMPRODUCT(((Resultados!$C$9:$C$108=Painel!$E$7)+(Resultados!$C$9:$C$108=""))*(Resultados!$G$9:$G$108<>"")*IFERROR(Resultados!$I$9:$I$108*1,0)))=0,"—",(SUMPRODUCT(((Resultados!$C$9:$C$108=Painel!$E$7)+(Resultados!$C$9:$C$108=""))*(Resultados!$G$9:$G$108<>"")*IFERROR(Resultados!$L$9:$L$108*1,0)))/(SUMPRODUCT(((Resultados!$C$9:$C$108=Painel!$E$7)+(Resultados!$C$9:$C$108=""))*(Resultados!$G$9:$G$108<>"")*IFERROR(Resultados!$I$9:$I$108*1,0)))) -> —
K31: =IF((SUMPRODUCT(((Resultados!$C$9:$C$108=Painel!$E$7)+(Resultados!$C$9:$C$108=""))*(Resultados!$G$9:$G$108<>"")*IFERROR((Resultados!$N$9:$N$108*1)<Calculadora!$E$12,0)))>0,(SUMPRODUCT(((Resultados!$C$9:$C$108=Painel!$E$7)+(Resultados!$C$9:$C$108=""))*(Resultados!$G$9:$G$108<>"")*IFERROR((Resultados!$N$9:$N$108*1)<Calculadora!$E$12,0)))&" venda(s) abaixo do piso","nenhuma venda abaixo do piso") -> nenhuma venda abaixo do piso
B33: EXPANSÃO · da aba Expansão
B34: OPORTUNIDADES ANOTADAS | E34: OPORTUNIDADES FECHADAS | H34: Meta: três oportunidades por cliente atendido. Faça as três perguntas da seção 11 na entrega de todo pedido.
B35: =SUMPRODUCT(((Expansão!$D$12:$D$111=Painel!$E$7)+(Expansão!$D$12:$D$111=""))*(Expansão!$C$12:$C$111<>"")*(Expansão!$C$12:$C$111<>"Exemplo · apague")) -> 0 | E35: =SUMPRODUCT(((Expansão!$D$12:$D$111=Painel!$E$7)+(Expansão!$D$12:$D$111=""))*(Expansão!$C$12:$C$111<>"")*(Expansão!$K$12:$K$111="Fechou")) -> 0
B38: DECISÃO DA SEMANA 2
B39: ='Missão 72h'!B29 -> RESPONDA O SELETOR | E39: ='Missão 72h'!D29 -> Responda as três perguntas na aba Seletor.
B42: Todo número deste painel é hipótese a validar com a sua impressora, o seu filamento e a sua região. LR Maker Lab · G-Code 3D · uso pessoal do comprador.

Sheet Missão 72h
B2: LR MAKER LAB · PAINEL G-CODE 3D
B3: Missão 72 horas
B4: Em 72 horas, você sai da impressora parada para três propostas entregues na mão de um comerciante.
J6: Ir para o Painel →
B7: Etapa | C7: Quando | D7: O que fazer | E7: Como saber que está feito | F7: Os números dizem | G7: Feito? | H7: Situação
B8: DIA 1 · PREPARAR
B9: 1 | C9: =IF(Painel!$K$7="","Dia 1",Painel!$K$7+0) -> Dia 1 | D9: ="Imprimir dois jogos do kit de amostra: "&IF(Biblioteca!$F$22=0,"",INDEX(Biblioteca!$H$8:$H$17,Biblioteca!$F$22))&IF(Biblioteca!$F$22=0,""," ("&IF(Biblioteca!$F$22=0,"",INDEX(Biblioteca!$I$8:$I$17,Biblioteca!$F$22))&")") -> Imprimir dois jogos do kit de amostra: | E9: Kit conferido, sem defeito, seção 06 do manual | H9: Não | I9: =IF(H9="Sim","Feito",IF(Painel!$K$7="","A fazer",IF(Painel!$K$7+0<TODAY(),"Atrasado",IF(Painel!$K$7+0=TODAY(),"Hoje","A fazer")))) -> A fazer
B10: 1 | C10: =IF(Painel!$K$7="","Dia 1",Painel!$K$7+0) -> Dia 1 | D10: ="Montar a embalagem e imprimir a proposta com os três níveis de preço" -> Montar a embalagem e imprimir a proposta com os três níveis de preço | E10: Três propostas impressas, com preço em cada nível | H10: Não | I10: =IF(H10="Sim","Feito",IF(Painel!$K$7="","A fazer",IF(Painel!$K$7+0<TODAY(),"Atrasado",IF(Painel!$K$7+0=TODAY(),"Hoje","A fazer")))) -> A fazer
B11: 1 | C11: =IF(Painel!$K$7="","Dia 1",Painel!$K$7+0) -> Dia 1 | D11: ="Listar 20 alvos na aba Alvos, com os sinais da seção 02 do manual" -> Listar 20 alvos na aba Alvos, com os sinais da seção 02 do manual | E11: 20 linhas na aba Alvos | G11: =(SUMPRODUCT(((Alvos!$C$13:$C$112=Painel!$E$7)+(Alvos!$C$13:$C$112=""))*(Alvos!$D$13:$D$112<>"")*1))&" de 20 alvos" -> 0 de 20 alvos | H11: Não | I11: =IF(H11="Sim","Feito",IF(Painel!$K$7="","A fazer",IF(Painel!$K$7+0<TODAY(),"Atrasado",IF(Painel!$K$7+0=TODAY(),"Hoje","A fazer")))) -> A fazer
B12: 1 | C12: =IF(Painel!$K$7="","Dia 1",Painel!$K$7+0) -> Dia 1 | D12: ="Decorar o script de 40 segundos e as seis respostas de objeção" -> Decorar o script de 40 segundos e as seis respostas de objeção | E12: Você fala em voz alta sem ler | H12: Não | I12: =IF(H12="Sim","Feito",IF(Painel!$K$7="","A fazer",IF(Painel!$K$7+0<TODAY(),"Atrasado",IF(Painel!$K$7+0=TODAY(),"Hoje","A fazer")))) -> A fazer
B13: DIA 2 · RUA
B14: 2 | C14: =IF(Painel!$K$7="","Dia 2",Painel!$K$7+1) -> Dia 2 | D14: ="Visitar 10 alvos"&IF(Biblioteca!$F$22=0,""," · "&IF(Biblioteca!$F$22=0,"",INDEX(Biblioteca!$G$8:$G$17,Biblioteca!$F$22))) -> Visitar 10 alvos | E14: 10 datas de visita na aba Alvos | G14: =(SUMPRODUCT(((Alvos!$C$13:$C$112=Painel!$E$7)+(Alvos!$C$13:$C$112=""))*(Alvos!$D$13:$D$112<>"")*(Alvos!$I$13:$I$112<>"")))&" de 10 visitas" -> 0 de 10 visitas | H14: Não | I14: =IF(H14="Sim","Feito",IF(Painel!$K$7="","A fazer",IF(Painel!$K$7+1<TODAY(),"Atrasado",IF(Painel!$K$7+1=TODAY(),"Hoje","A fazer")))) -> A fazer
B15: 2 | C15: =IF(Painel!$K$7="","Dia 2",Painel!$K$7+1) -> Dia 2 | D15: ="Entregar 3 propostas na mão de quem decide" -> Entregar 3 propostas na mão de quem decide | E15: 3 datas em Proposta entregue | G15: =(SUMPRODUCT(((Alvos!$C$13:$C$112=Painel!$E$7)+(Alvos!$C$13:$C$112=""))*(Alvos!$D$13:$D$112<>"")*(Alvos!$K$13:$K$112<>"")))&" de 3 propostas" -> 0 de 3 propostas | H15: Não | I15: =IF(H15="Sim","Feito",IF(Painel!$K$7="","A fazer",IF(Painel!$K$7+1<TODAY(),"Atrasado",IF(Painel!$K$7+1=TODAY(),"Hoje","A fazer")))) -> A fazer
B16: 2 | C16: =IF(Painel!$K$7="","Dia 2",Painel!$K$7+1) -> Dia 2 | D16: ="Anotar toda objeção com as palavras exatas, no carro" -> Anotar toda objeção com as palavras exatas, no carro | E16: Coluna Objeção preenchida | H16: Não | I16: =IF(H16="Sim","Feito",IF(Painel!$K$7="","A fazer",IF(Painel!$K$7+1<TODAY(),"Atrasado",IF(Painel!$K$7+1=TODAY(),"Hoje","A fazer")))) -> A fazer
B17: DIA 3 · FECHAR
B18: 3 | C18: =IF(Painel!$K$7="","Dia 3",Painel!$K$7+2) -> Dia 3 | D18: ="Mandar o follow-up para as três propostas (seção 10)" -> Mandar o follow-up para as três propostas (seção 10) | E18: Status Follow-up 48h feito | H18: Não | I18: =IF(H18="Sim","Feito",IF(Painel!$K$7="","A fazer",IF(Painel!$K$7+2<TODAY(),"Atrasado",IF(Painel!$K$7+2=TODAY(),"Hoje","A fazer")))) -> A fazer
B19: 3 | C19: =IF(Painel!$K$7="","Dia 3",Painel!$K$7+2) -> Dia 3 | D19: ="Registrar tudo na aba Alvos, com a data de volta de cada um" -> Registrar tudo na aba Alvos, com a data de volta de cada um | E19: Nenhuma visita só no papel | H19: Não | I19: =IF(H19="Sim","Feito",IF(Painel!$K$7="","A fazer",IF(Painel!$K$7+2<TODAY(),"Atrasado",IF(Painel!$K$7+2=TODAY(),"Hoje","A fazer")))) -> A fazer
B20: 3 | C20: =IF(Painel!$K$7="","Dia 3",Painel!$K$7+2) -> Dia 3 | D20: ="Anotar as oportunidades ouvidas no balcão" -> Anotar as oportunidades ouvidas no balcão | E20: Coluna Oportunidade ouvida | H20: Não | I20: =IF(H20="Sim","Feito",IF(Painel!$K$7="","A fazer",IF(Painel!$K$7+2<TODAY(),"Atrasado",IF(Painel!$K$7+2=TODAY(),"Hoje","A fazer")))) -> A fazer
B21: 3 | C21: =IF(Painel!$K$7="","Dia 3",Painel!$K$7+2) -> Dia 3 | D21: ="Marcar na agenda a data da segunda leva de 10 visitas" -> Marcar na agenda a data da segunda leva de 10 visitas | E21: Data escrita na agenda | H21: Não | I21: =IF(H21="Sim","Feito",IF(Painel!$K$7="","A fazer",IF(Painel!$K$7+2<TODAY(),"Atrasado",IF(Painel!$K$7+2=TODAY(),"Hoje","A fazer")))) -> A fazer
B22: SEMANA 2 · CONTINUAR
B23: 4 | C23: =IF(Painel!$K$7="","Dias 4 a 10",Painel!$K$7+3) -> Dias 4 a 10 | D23: ="Voltar nos alvos com amostra ou proposta, no dia combinado" -> Voltar nos alvos com amostra ou proposta, no dia combinado | E23: Próximo contato em dia na aba Alvos | G23: =(SUMPRODUCT(((Alvos!$C$13:$C$112=Painel!$E$7)+(Alvos!$C$13:$C$112=""))*(Alvos!$D$13:$D$112<>"")*(Alvos!$P$13:$P$112<>"")*(Alvos!$P$13:$P$112<=TODAY())))&" contatos para hoje ou atrasados" -> 0 contatos para hoje ou atrasados | H23: Não | I23: =IF(H23="Sim","Feito",IF(Painel!$K$7="","A fazer",IF(Painel!$K$7+3<TODAY(),"Atrasado",IF(Painel!$K$7+3=TODAY(),"Hoje","A fazer")))) -> A fazer
B24: 4 | C24: =IF(Painel!$K$7="","Dias 4 a 10",Painel!$K$7+3) -> Dias 4 a 10 | D24: ="Fazer a segunda leva de 10 visitas, já com as objeções reais anotadas" -> Fazer a segunda leva de 10 visitas, já com as objeções reais anotadas | E24: 20 visitas no total | G24: =(SUMPRODUCT(((Alvos!$C$13:$C$112=Painel!$E$7)+(Alvos!$C$13:$C$112=""))*(Alvos!$D$13:$D$112<>"")*(Alvos!$I$13:$I$112<>"")))&" de 20 visitas" -> 0 de 20 visitas | H24: Não | I24: =IF(H24="Sim","Feito",IF(Painel!$K$7="","A fazer",IF(Painel!$K$7+3<TODAY(),"Atrasado",IF(Painel!$K$7+3=TODAY(),"Hoje","A fazer")))) -> A fazer
B25: 4 | C25: =IF(Painel!$K$7="","Dias 4 a 10",Painel!$K$7+3) -> Dias 4 a 10 | D25: ="Produzir o primeiro pedido e conferir com a lista da seção 05" -> Produzir o primeiro pedido e conferir com a lista da seção 05 | E25: Venda registrada na aba Resultados | G25: =(SUMPRODUCT(((Resultados!$C$9:$C$108=Painel!$E$7)+(Resultados!$C$9:$C$108=""))*(Resultados!$G$9:$G$108<>"")*1))&" vendas registradas" -> 0 vendas registradas | H25: Não | I25: =IF(H25="Sim","Feito",IF(Painel!$K$7="","A fazer",IF(Painel!$K$7+3<TODAY(),"Atrasado",IF(Painel!$K$7+3=TODAY(),"Hoje","A fazer")))) -> A fazer
B26: 4 | C26: =IF(Painel!$K$7="","Dias 4 a 10",Painel!$K$7+3) -> Dias 4 a 10 | D26: ="Na entrega, fazer as três perguntas da seção 11" -> Na entrega, fazer as três perguntas da seção 11 | E26: Linhas na aba Expansão | G26: =(SUMPRODUCT(((Expansão!$D$12:$D$111=Painel!$E$7)+(Expansão!$D$12:$D$111=""))*(Expansão!$C$12:$C$111<>"")*(Expansão!$C$12:$C$111<>"Exemplo · apague")))&" oportunidades anotadas" -> 0 oportunidades anotadas | H26: Não | I26: =IF(H26="Sim","Feito",IF(Painel!$K$7="","A fazer",IF(Painel!$K$7+3<TODAY(),"Atrasado",IF(Painel!$K$7+3=TODAY(),"Hoje","A fazer")))) -> A fazer
B28: DECISÃO DA SEMANA 2 · o Painel lê os seus números
B29: =IF(Biblioteca!$F$22=0,"RESPONDA O SELETOR",IF((SUMPRODUCT(((Alvos!$C$13:$C$112=Painel!$E$7)+(Alvos!$C$13:$C$112=""))*(Alvos!$D$13:$D$112<>"")*(Alvos!$M$13:$M$112="Fechou")))+(SUMPRODUCT(((Resultados!$C$9:$C$108=Painel!$E$7)+(Resultados!$C$9:$C$108=""))*(Resultados!$G$9:$G$108<>"")*1))>=1,"ESCALAR",IF(AND((SUMPRODUCT(((Alvos!$C$13:$C$112=Painel!$E$7)+(Alvos!$C$13:$C$112=""))*(Alvos!$D$13:$D$112<>"")*(Alvos!$I$13:$I$112<>"")))>=20,(SUMPRODUCT(((Alvos!$C$13:$C$112=Painel!$E$7)+(Alvos!$C$13:$C$112=""))*(Alvos!$D$13:$D$112<>"")*(Alvos!$K$13:$K$112<>"")))=0),"TROCAR",IF((SUMPRODUCT(((Alvos!$C$13:$C$112=Painel!$E$7)+(Alvos!$C$13:$C$112=""))*(Alvos!$D$13:$D$112<>"")*(Alvos!$K$13:$K$112<>"")))>=3,"AJUSTAR O FOLLOW-UP",IF((SUMPRODUCT(((Alvos!$C$13:$C$112=Painel!$E$7)+(Alvos!$C$13:$C$112=""))*(Alvos!$D$13:$D$112<>"")*(Alvos!$I$13:$I$112<>"")))>=10,"AJUSTAR A ABORDAGEM","SIGA A MISSÃO"))))) -> RESPONDA O SELETOR | D29: =IF(Biblioteca!$F$22=0,"Responda as três perguntas na aba Seletor.",IF((SUMPRODUCT(((Alvos!$C$13:$C$112=Painel!$E$7)+(Alvos!$C$13:$C$112=""))*(Alvos!$D$13:$D$112<>"")*(Alvos!$M$13:$M$112="Fechou")))+(SUMPRODUCT(((Resultados!$C$9:$C$108=Painel!$E$7)+(Resultados!$C$9:$C$108=""))*(Resultados!$G$9:$G$108<>"")*1))>=1,"Houve venda. Produza, entregue no prazo, faça as três perguntas da seção 11 e faça a segunda leva de visitas no mesmo bairro.",IF(AND((SUMPRODUCT(((Alvos!$C$13:$C$112=Painel!$E$7)+(Alvos!$C$13:$C$112=""))*(Alvos!$D$13:$D$112<>"")*(Alvos!$I$13:$I$112<>"")))>=20,(SUMPRODUCT(((Alvos!$C$13:$C$112=Painel!$E$7)+(Alvos!$C$13:$C$112=""))*(Alvos!$D$13:$D$112<>"")*(Alvos!$K$13:$K$112<>"")))=0),"Duas levas completas sem nenhuma proposta. Troque para "&IF(Biblioteca!$F$22=0,"",INDEX(Biblioteca!$K$8:$K$17,Biblioteca!$F$22))&". Leve as objeções que você anotou: elas valem para o próximo.",IF((SUMPRODUCT(((Alvos!$C$13:$C$112=Painel!$E$7)+(Alvos!$C$13:$C$112=""))*(Alvos!$D$13:$D$112<>"")*(Alvos!$K$13:$K$112<>"")))>=3,"As propostas estão na mão. Agora é follow-up: 48h, 7 dias e a mensagem final, como na seção 10. Não troque de G-Code antes disso.",IF((SUMPRODUCT(((Alvos!$C$13:$C$112=Painel!$E$7)+(Alvos!$C$13:$C$112=""))*(Alvos!$D$13:$D$112<>"")*(Alvos!$I$13:$I$112<>"")))>=10,"Você visitou, mas ainda não chegou a 3 propostas. Releia as objeções anotadas, confira o horário de visita e faça a segunda leva de 10.","Siga a próxima ação do Painel. A decisão fica valendo depois das primeiras 10 visitas."))))) -> Responda as três perguntas na aba Seletor.
B32: ESCALAR | E32: AJUSTAR | H32: TROCAR
B33: Houve venda: repita no mesmo bairro. | E33: Propostas na mão ou visitas sem proposta: ajuste antes de trocar. | H33: Só depois de 20 visitas sem nenhuma proposta.

Sheet Alvos
B2: LR MAKER LAB · PAINEL G-CODE 3D
B3: Alvos
B4: Seus comércios, da lista até a proposta na mão. Preencha no carro, logo depois de cada visita.
Q6: Ir para o Painel →
B7: Resumo do G-Code escolhido no Painel
B8: ALVOS LISTADOS | D8: VISITADOS | G8: AMOSTRAS DEIXADAS | I8: PROPOSTAS NA MÃO | L8: FECHARAM | O8: CONTATOS PARA HOJE
B9: =SUMPRODUCT(((Alvos!$C$13:$C$112=Painel!$E$7)+(Alvos!$C$13:$C$112=""))*(Alvos!$D$13:$D$112<>"")*1) -> 0 | D9: =SUMPRODUCT(((Alvos!$C$13:$C$112=Painel!$E$7)+(Alvos!$C$13:$C$112=""))*(Alvos!$D$13:$D$112<>"")*(Alvos!$I$13:$I$112<>"")) -> 0 | G9: =SUMPRODUCT(((Alvos!$C$13:$C$112=Painel!$E$7)+(Alvos!$C$13:$C$112=""))*(Alvos!$D$13:$D$112<>"")*(Alvos!$J$13:$J$112="Sim")) -> 0 | I9: =SUMPRODUCT(((Alvos!$C$13:$C$112=Painel!$E$7)+(Alvos!$C$13:$C$112=""))*(Alvos!$D$13:$D$112<>"")*(Alvos!$K$13:$K$112<>"")) -> 0 | L9: =SUMPRODUCT(((Alvos!$C$13:$C$112=Painel!$E$7)+(Alvos!$C$13:$C$112=""))*(Alvos!$D$13:$D$112<>"")*(Alvos!$M$13:$M$112="Fechou")) -> 0 | O9: =SUMPRODUCT(((Alvos!$C$13:$C$112=Painel!$E$7)+(Alvos!$C$13:$C$112=""))*(Alvos!$D$13:$D$112<>"")*(Alvos!$P$13:$P$112<>"")*(Alvos!$P$13:$P$112<=TODAY())) -> 0
B10: meta: 20 | D10: meta: 10 | G10: nas mãos certas | I10: meta: 3 | L10: referência: 1 | O10: ou atrasados
B11: G-Code em branco conta para o G-Code do Painel. Status: A visitar → Visitado → Amostra deixada → Proposta entregue → Follow-up 48h → 7 dias → Fechou ou Não agora. O Próximo contato é calculado sozinho e fica verde no dia.
B12: # | C12: G-Code | D12: Comércio | E12: Bairro | F12: Quem decide | G12: WhatsApp ou Instagram | H12: Nota no Google | I12: Data da visita | J12: Deixou amostra? | K12: Proposta entregue em | L12: Valor proposto | M12: Status | N12: Objeção, nas palavras exatas | O12: Volto em | P12: Próximo contato | Q12: Oportunidade ouvida
B13: =IF(D13="","",ROW()-12) -> 1 | C13: Exemplo · apague | D13: Confeitaria Doce Ana | E13: Centro | F13: Ana, a dona | G13: @doceana | H13: 4.6 | I13: 46301 | J13: Sim | K13: 46301 | L13: 180 | M13: Proposta entregue | N13: Vou ver com meu marido. | P13: =IF(OR(D13="",M13="Fechou",M13="Não agora"),"",IF(O13<>"",O13,IF(K13="","",IF(M13="Proposta entregue",K13+2,IF(M13="Follow-up 48h feito",K13+7,IF(M13="Follow-up 7 dias feito",K13+21,"")))))) -> 46303 | Q13: Porta-cartão com QR do Pix
B14: =IF(D14="","",ROW()-12) | P14: =IF(OR(D14="",M14="Fechou",M14="Não agora"),"",IF(O14<>"",O14,IF(K14="","",IF(M14="Proposta entregue",K14+2,IF(M14="Follow-up 48h feito",K14+7,IF(M14="Follow-up 7 dias feito",K14+21,""))))))
B15: =IF(D15="","",ROW()-12) | P15: =IF(OR(D15="",M15="Fechou",M15="Não agora"),"",IF(O15<>"",O15,IF(K15="","",IF(M15="Proposta entregue",K15+2,IF(M15="Follow-up 48h feito",K15+7,IF(M15="Follow-up 7 dias feito",K15+21,""))))))
B16: =IF(D16="","",ROW()-12) | P16: =IF(OR(D16="",M16="Fechou",M16="Não agora"),"",IF(O16<>"",O16,IF(K16="","",IF(M16="Proposta entregue",K16+2,IF(M16="Follow-up 48h feito",K16+7,IF(M16="Follow-up 7 dias feito",K16+21,""))))))
B17: =IF(D17="","",ROW()-12) | P17: =IF(OR(D17="",M17="Fechou",M17="Não agora"),"",IF(O17<>"",O17,IF(K17="","",IF(M17="Proposta entregue",K17+2,IF(M17="Follow-up 48h feito",K17+7,IF(M17="Follow-up 7 dias feito",K17+21,""))))))
B18: =IF(D18="","",ROW()-12) | P18: =IF(OR(D18="",M18="Fechou",M18="Não agora"),"",IF(O18<>"",O18,IF(K18="","",IF(M18="Proposta entregue",K18+2,IF(M18="Follow-up 48h feito",K18+7,IF(M18="Follow-up 7 dias feito",K18+21,""))))))
B19: =IF(D19="","",ROW()-12) | P19: =IF(OR(D19="",M19="Fechou",M19="Não agora"),"",IF(O19<>"",O19,IF(K19="","",IF(M19="Proposta entregue",K19+2,IF(M19="Follow-up 48h feito",K19+7,IF(M19="Follow-up 7 dias feito",K19+21,""))))))
B20: =IF(D20="","",ROW()-12) | P20: =IF(OR(D20="",M20="Fechou",M20="Não agora"),"",IF(O20<>"",O20,IF(K20="","",IF(M20="Proposta entregue",K20+2,IF(M20="Follow-up 48h feito",K20+7,IF(M20="Follow-up 7 dias feito",K20+21,""))))))
B21: =IF(D21="","",ROW()-12) | P21: =IF(OR(D21="",M21="Fechou",M21="Não agora"),"",IF(O21<>"",O21,IF(K21="","",IF(M21="Proposta entregue",K21+2,IF(M21="Follow-up 48h feito",K21+7,IF(M21="Follow-up 7 dias feito",K21+21,""))))))
B22: =IF(D22="","",ROW()-12) | P22: =IF(OR(D22="",M22="Fechou",M22="Não agora"),"",IF(O22<>"",O22,IF(K22="","",IF(M22="Proposta entregue",K22+2,IF(M22="Follow-up 48h feito",K22+7,IF(M22="Follow-up 7 dias feito",K22+21,""))))))
B23: =IF(D23="","",ROW()-12) | P23: =IF(OR(D23="",M23="Fechou",M23="Não agora"),"",IF(O23<>"",O23,IF(K23="","",IF(M23="Proposta entregue",K23+2,IF(M23="Follow-up 48h feito",K23+7,IF(M23="Follow-up 7 dias feito",K23+21,""))))))
B24: =IF(D24="","",ROW()-12) | P24: =IF(OR(D24="",M24="Fechou",M24="Não agora"),"",IF(O24<>"",O24,IF(K24="","",IF(M24="Proposta entregue",K24+2,IF(M24="Follow-up 48h feito",K24+7,IF(M24="Follow-up 7 dias feito",K24+21,""))))))
B25: =IF(D25="","",ROW()-12) | P25: =IF(OR(D25="",M25="Fechou",M25="Não agora"),"",IF(O25<>"",O25,IF(K25="","",IF(M25="Proposta entregue",K25+2,IF(M25="Follow-up 48h feito",K25+7,IF(M25="Follow-up 7 dias feito",K25+21,""))))))
... B112: =IF(D112="","",ROW()-12) | P112: =IF(OR(D112="",M112="Fechou",M112="Não agora"),"",IF(O112<>"",O112,IF(K112="","",IF(M112="Proposta entregue",K112+2,IF(M112="Follow-up 48h feito",K112+7,IF(M112="Follow-up 7 dias feito",K112+21,""))))))

Sheet Calculadora
B2: LR MAKER LAB · PAINEL G-CODE 3D
B3: Calculadora
B4: Faça a conta antes de responder qualquer orçamento: custo real, piso, preço sugerido e retorno por hora.
K6: Ir para o Painel →
B7: Seus números · preencha uma vez
B8: Preço do filamento | E8: 120 | F8: por kg. Troque pelo que você paga.
B9: Perda e falhas | E9: 0.15 | F9: sobre o filamento: purga, suporte e peça perdida. Mesmo valor dos manuais.
B10: Potência média da impressora | E10: 150 | F10: veja na etiqueta da fonte.
B11: Tarifa de energia | E11: 0.95 | F11: por kWh, com impostos. Veja na conta de luz.
B12: Piso por hora de máquina | E12: 15 | F12: regra do G-Code 3D: nenhum pedido abaixo disso.
B13: Sua meta por hora | E13: 40 | F13: quanto você quer ganhar por hora de máquina. Define o preço sugerido.
B15: Simule um pedido
B16: O que é o pedido | E16: 10 suportes de mesa | F16: Filamento com perda | H16: =E17/1000*Calculadora!$E$8*(1+Calculadora!$E$9) -> 16.56
B17: Filamento do pedido inteiro | E17: 120 | F17: Energia | H17: =E18*Calculadora!$E$10/1000*Calculadora!$E$11 -> 0.49875
B18: Horas de máquina do pedido | E18: 3.5 | F18: Custo real | H18: =H16+H17+E19 -> 25.05875
B19: Extras: embalagem, argola, ímã, adesivo | E19: 8 | F19: Piso (custo + horas × piso) | H19: =H18+E18*Calculadora!$E$12 -> 77.55875
B20: Quantidade de peças | E20: 10 | F20: Preço sugerido (custo + horas × meta) | H20: =H18+E18*Calculadora!$E$13 -> 165.05875
B21: Seu preço para o pedido | E21: 200 | F21: Margem | H21: =E21-H18 -> 174.94125
F22: Retorno por hora de máquina | H22: =IF(E18=0,"",H21/E18) -> 49.983214
F23: Preço por peça | H23: =IF(E20=0,"",E21/E20) -> 20
B25: =IF(E21="","",IF(H22<Calculadora!$E$12,"ABAIXO DO PISO. Não feche por esse preço: suba o preço ou mude a peça.",IF(H22<Calculadora!$E$13,"Acima do piso e abaixo da sua meta. Dá para fechar, mas veja se cabe subir o preço.","Na meta. Pode fechar."))) -> Na meta. Pode fechar.
B28: Horas de máquina: use o tempo do fatiador para o pedido inteiro. O tempo de arte, mensagem e ida à loja não entra aqui; é por causa dele que o piso existe. Todo número é hipótese a validar com a sua impressora e a sua região.

Sheet Resultados
B2: LR MAKER LAB · PAINEL G-CODE 3D
B3: Resultados
B4: Cada venda fechada, com o custo real e o retorno por hora de verdade. Usa os seus números da Calculadora.
P6: Ir para o Painel →
B7: G-Code em branco conta para o G-Code do Painel. O retorno por hora fica vermelho abaixo do piso.
B8: Data | C8: G-Code | D8: Cliente | E8: O que vendeu | F8: Qtd | G8: Valor recebido | H8: Filamento (g) | I8: Horas de máquina | J8: Extras | K8: Custo real | L8: Lucro | M8: Margem | N8: Retorno por hora | O8: Situação | P8: Pediu de novo?
B9: 46309 | C9: Exemplo · apague | D9: Confeitaria Doce Ana | E9: Kit de 3 cortadores e carimbo | F9: 3 | G9: 180 | H9: 90 | I9: 2.5 | J9: 6 | K9: =IF(G9="","",H9/1000*Calculadora!$E$8*(1+Calculadora!$E$9)+I9*Calculadora!$E$10/1000*Calculadora!$E$11+J9) -> 18.77625 | L9: =IF(G9="","",G9-K9) -> 161.22375 | M9: =IF(OR(G9="",G9=0),"",L9/G9) -> 0.8956875 | N9: =IF(OR(G9="",I9="",I9=0),"",L9/I9) -> 64.4895 | O9: =IF(N9="","",IF(N9<Calculadora!$E$12,"Abaixo do piso",IF(N9<Calculadora!$E$13,"Acima do piso","Na meta"))) -> Na meta | P9: Sim
K10: =IF(G10="","",H10/1000*Calculadora!$E$8*(1+Calculadora!$E$9)+I10*Calculadora!$E$10/1000*Calculadora!$E$11+J10) | L10: =IF(G10="","",G10-K10) | M10: =IF(OR(G10="",G10=0),"",L10/G10) | N10: =IF(OR(G10="",I10="",I10=0),"",L10/I10) | O10: =IF(N10="","",IF(N10<Calculadora!$E$12,"Abaixo do piso",IF(N10<Calculadora!$E$13,"Acima do piso","Na meta")))
K11: =IF(G11="","",H11/1000*Calculadora!$E$8*(1+Calculadora!$E$9)+I11*Calculadora!$E$10/1000*Calculadora!$E$11+J11) | L11: =IF(G11="","",G11-K11) | M11: =IF(OR(G11="",G11=0),"",L11/G11) | N11: =IF(OR(G11="",I11="",I11=0),"",L11/I11) | O11: =IF(N11="","",IF(N11<Calculadora!$E$12,"Abaixo do piso",IF(N11<Calculadora!$E$13,"Acima do piso","Na meta")))
K12: =IF(G12="","",H12/1000*Calculadora!$E$8*(1+Calculadora!$E$9)+I12*Calculadora!$E$10/1000*Calculadora!$E$11+J12) | L12: =IF(G12="","",G12-K12) | M12: =IF(OR(G12="",G12=0),"",L12/G12) | N12: =IF(OR(G12="",I12="",I12=0),"",L12/I12) | O12: =IF(N12="","",IF(N12<Calculadora!$E$12,"Abaixo do piso",IF(N12<Calculadora!$E$13,"Acima do piso","Na meta")))
K13: =IF(G13="","",H13/1000*Calculadora!$E$8*(1+Calculadora!$E$9)+I13*Calculadora!$E$10/1000*Calculadora!$E$11+J13) | L13: =IF(G13="","",G13-K13) | M13: =IF(OR(G13="",G13=0),"",L13/G13) | N13: =IF(OR(G13="",I13="",I13=0),"",L13/I13) | O13: =IF(N13="","",IF(N13<Calculadora!$E$12,"Abaixo do piso",IF(N13<Calculadora!$E$13,"Acima do piso","Na meta")))
K14: =IF(G14="","",H14/1000*Calculadora!$E$8*(1+Calculadora!$E$9)+I14*Calculadora!$E$10/1000*Calculadora!$E$11+J14) | L14: =IF(G14="","",G14-K14) | M14: =IF(OR(G14="",G14=0),"",L14/G14) | N14: =IF(OR(G14="",I14="",I14=0),"",L14/I14) | O14: =IF(N14="","",IF(N14<Calculadora!$E$12,"Abaixo do piso",IF(N14<Calculadora!$E$13,"Acima do piso","Na meta")))
K15: =IF(G15="","",H15/1000*Calculadora!$E$8*(1+Calculadora!$E$9)+I15*Calculadora!$E$10/1000*Calculadora!$E$11+J15) | L15: =IF(G15="","",G15-K15) | M15: =IF(OR(G15="",G15=0),"",L15/G15) | N15: =IF(OR(G15="",I15="",I15=0),"",L15/I15) | O15: =IF(N15="","",IF(N15<Calculadora!$E$12,"Abaixo do piso",IF(N15<Calculadora!$E$13,"Acima do piso","Na meta")))
K16: =IF(G16="","",H16/1000*Calculadora!$E$8*(1+Calculadora!$E$9)+I16*Calculadora!$E$10/1000*Calculadora!$E$11+J16) | L16: =IF(G16="","",G16-K16) | M16: =IF(OR(G16="",G16=0),"",L16/G16) | N16: =IF(OR(G16="",I16="",I16=0),"",L16/I16) | O16: =IF(N16="","",IF(N16<Calculadora!$E$12,"Abaixo do piso",IF(N16<Calculadora!$E$13,"Acima do piso","Na meta")))
K17: =IF(G17="","",H17/1000*Calculadora!$E$8*(1+Calculadora!$E$9)+I17*Calculadora!$E$10/1000*Calculadora!$E$11+J17) | L17: =IF(G17="","",G17-K17) | M17: =IF(OR(G17="",G17=0),"",L17/G17) | N17: =IF(OR(G17="",I17="",I17=0),"",L17/I17) | O17: =IF(N17="","",IF(N17<Calculadora!$E$12,"Abaixo do piso",IF(N17<Calculadora!$E$13,"Acima do piso","Na meta")))
K18: =IF(G18="","",H18/1000*Calculadora!$E$8*(1+Calculadora!$E$9)+I18*Calculadora!$E$10/1000*Calculadora!$E$11+J18) | L18: =IF(G18="","",G18-K18) | M18: =IF(OR(G18="",G18=0),"",L18/G18) | N18: =IF(OR(G18="",I18="",I18=0),"",L18/I18) | O18: =IF(N18="","",IF(N18<Calculadora!$E$12,"Abaixo do piso",IF(N18<Calculadora!$E$13,"Acima do piso","Na meta")))
K19: =IF(G19="","",H19/1000*Calculadora!$E$8*(1+Calculadora!$E$9)+I19*Calculadora!$E$10/1000*Calculadora!$E$11+J19) | L19: =IF(G19="","",G19-K19) | M19: =IF(OR(G19="",G19=0),"",L19/G19) | N19: =IF(OR(G19="",I19="",I19=0),"",L19/I19) | O19: =IF(N19="","",IF(N19<Calculadora!$E$12,"Abaixo do piso",IF(N19<Calculadora!$E$13,"Acima do piso","Na meta")))
K20: =IF(G20="","",H20/1000*Calculadora!$E$8*(1+Calculadora!$E$9)+I20*Calculadora!$E$10/1000*Calculadora!$E$11+J20) | L20: =IF(G20="","",G20-K20) | M20: =IF(OR(G20="",G20=0),"",L20/G20) | N20: =IF(OR(G20="",I20="",I20=0),"",L20/I20) | O20: =IF(N20="","",IF(N20<Calculadora!$E$12,"Abaixo do piso",IF(N20<Calculadora!$E$13,"Acima do piso","Na meta")))
K21: =IF(G21="","",H21/1000*Calculadora!$E$8*(1+Calculadora!$E$9)+I21*Calculadora!$E$10/1000*Calculadora!$E$11+J21) | L21: =IF(G21="","",G21-K21) | M21: =IF(OR(G21="",G21=0),"",L21/G21) | N21: =IF(OR(G21="",I21="",I21=0),"",L21/I21) | O21: =IF(N21="","",IF(N21<Calculadora!$E$12,"Abaixo do piso",IF(N21<Calculadora!$E$13,"Acima do piso","Na meta")))
... K108: =IF(G108="","",H108/1000*Calculadora!$E$8*(1+Calculadora!$E$9)+I108*Calculadora!$E$10/1000*Calculadora!$E$11+J108) | L108: =IF(G108="","",G108-K108) | M108: =IF(OR(G108="",G108=0),"",L108/G108) | N108: =IF(OR(G108="",I108="",I108=0),"",L108/I108) | O108: =IF(N108="","",IF(N108<Calculadora!$E$12,"Abaixo do piso",IF(N108<Calculadora!$E$13,"Acima do piso","Na meta")))

Sheet Expansão
B2: LR MAKER LAB · PAINEL G-CODE 3D
B3: Expansão
B4: A primeira venda abre a porta. Na entrega, faça as três perguntas da seção 11 do manual e anote tudo aqui.
L6: Ir para o Painel →
B7: Meta: três oportunidades por cliente atendido. Quem já comprou de você e recebeu no prazo compra de novo sem visita fria. Cliente que ainda não tem três linhas aqui ainda tem venda escondida.
B11: Data | C11: Cliente | D11: G-Code | E11: Pergunta | F11: O que ele respondeu | G11: Oportunidade | H11: Valor estimado | I11: Próxima ação | J11: Prazo | K11: Status | L11: Oportunidades deste cliente
B12: 46315 | C12: Exemplo · apague | E12: Indicação | F12: "A gente compra sobremesa da confeitaria da esquina." | G12: Indicação: confeitaria parceira | H12: 150 | I12: Pedir o contato e levar o kit | J12: 46319 | K12: Anotada | L12: =IF(C12="","",COUNTIF($C$12:$C$111,C12)) -> 1
L13: =IF(C13="","",COUNTIF($C$12:$C$111,C13))
L14: =IF(C14="","",COUNTIF($C$12:$C$111,C14))
L15: =IF(C15="","",COUNTIF($C$12:$C$111,C15))
L16: =IF(C16="","",COUNTIF($C$12:$C$111,C16))
L17: =IF(C17="","",COUNTIF($C$12:$C$111,C17))
L18: =IF(C18="","",COUNTIF($C$12:$C$111,C18))
L19: =IF(C19="","",COUNTIF($C$12:$C$111,C19))
L20: =IF(C20="","",COUNTIF($C$12:$C$111,C20))
L21: =IF(C21="","",COUNTIF($C$12:$C$111,C21))
L22: =IF(C22="","",COUNTIF($C$12:$C$111,C22))
L23: =IF(C23="","",COUNTIF($C$12:$C$111,C23))
L24: =IF(C24="","",COUNTIF($C$12:$C$111,C24))
... L111: =IF(C111="","",COUNTIF($C$12:$C$111,C111))

Sheet Biblioteca
B2: LR MAKER LAB · PAINEL G-CODE 3D
B3: Biblioteca dos 10 G-Codes
B4: Os dados que alimentam o Painel. Vêm dos manuais e são hipóteses a validar na sua região.
N6: Ir para o Painel →
B7: Código | C7: G-Code | D7: Nível | E7: Ticket do 1º pedido | F7: Retorno por hora | G7: Quando visitar | H7: Kit de amostra: imprima… | I7: Máquina do kit | J7: Número honesto (expectativa, não promessa) | K7: Se precisar trocar | L7: Por que o Seletor indica | M7: Dia 2 pode cair em (1 = segunda) | N7: Melhor dia para começar
B8: G-01 | C8: G-01 · Confeitarias e docerias | D8: Nível 1 | E8: R$ 90 a 400 | F8: ~R$ 65/h | G8: terça a quinta, das 14h às 16h | H8: as três peças em PETG | I8: 1h35 de máquina · 32 g | J8: 10 visitas → 3 propostas → 1 venda | K8: G-04 · Restaurantes, cafés e bares | L8: Pouca máquina e sem CAD pedem peça pequena, arte simples e pedido que cabe numa noite. Cortador, carimbo e topo de bolo são isso. | M8: 234 | N8: segunda ou terça
B9: G-02 | C9: G-02 · Nail designers e salões | D9: Nível 1 | E9: R$ 90 a 300 | F9: ~R$ 21/h | G9: terça ou quarta, das 9h às 10h30 | H9: o mini mostruário e a plaquinha | I9: 3h00 de máquina · 60 g | J9: 10 abordagens → 3 propostas → 1 venda, mais indicações | K9: G-05 · Semijoias e acessórios | L9: Fica na biblioteca: abra depois da primeira venda. | M9: 23 | N9: segunda ou terça
B10: G-03 | C10: G-03 · Pet shops | D10: Nível 1 | E10: R$ 160 a 800 | F10: ~R$ 58/h | G10: terça a quinta, das 14h às 16h | H10: as tags e o mini display | I10: 2h10 de máquina · 45 g | J10: 10 visitas → 3 mini displays deixados → 1 lote em consignação | K10: G-09 · Papelarias e festa | L10: Com pouca máquina, quem revende trabalha por você: o pet shop vende as suas tags no balcão, e a reposição chega sem nova visita. | M10: 234 | N10: segunda, terça ou quarta
B11: G-04 | C11: G-04 · Restaurantes, cafés e bares | D11: Nível 1 | E11: R$ 150 a 700 | F11: ~R$ 52/h | G11: terça a quinta, das 15h às 17h | H11: o suporte, com o QR testado em 3 celulares | I11: 1h50 de máquina · 59 g | J11: 10 visitas → 3 casas com suporte em teste → 1 venda | K11: G-01 · Confeitarias e docerias | L11: Máquina média, sem CAD e para quem usa: suporte de QR para avaliação no Google, cardápio e Pix. A dor é a nota no Google, e o dono sabe disso. | M11: 234 | N11: segunda, terça ou quarta
B12: G-05 | C12: G-05 · Semijoias e acessórios | D12: Nível 2 | E12: R$ 150 a 700 | F12: ~R$ 25/h | G12: terça a quinta, das 10h às 12h | H12: o kit em PLA fosco e silk | I12: 2h40 de máquina · 60 g | J12: 10 visitas → 3 propostas → 1 venda até o próximo lançamento | K12: G-02 · Nail designers e salões | L12: Fica na biblioteca: abra depois da primeira venda. | M12: 234 | N12: segunda, terça ou quarta
B13: G-06 | C13: G-06 · Lojas de celular e assistências | D13: Nível 2 | E13: R$ 120 a 700 | F13: ~R$ 30/h | G13: terça a quinta, das 10h às 12h | H13: o expositor e a mini bandeja | I13: 2h20 de máquina · 65 g | J13: 10 visitas → 3 lojas medidas → 1 venda | K13: G-10 · Oficinas e pequena indústria | L13: Fica na biblioteca: abra depois da primeira venda. | M13: 234 | N13: segunda, terça ou quarta
B14: G-07 | C14: G-07 · Academias, boxes e escolas esportivas | D14: Nível 2 | E14: R$ 250 a 1.500 | F14: ~R$ 52/h | G14: fora do pico: 10h às 12h ou 14h às 16h | H14: a medalha com o nome do desafio deles | I14: 2h50 de máquina · 64 g | J14: 10 visitas → 3 datas de desafio anotadas → 1 pedido | K14: G-08 · Imobiliárias e corretores | L14: Com mais de 8h livres por dia, você aguenta um pacote de 14h de máquina. Medalha de desafio interno tem data marcada e se repete a cada desafio. | M14: 1234 | N14: domingo, segunda, terça ou quarta
B15: G-08 | C15: G-08 · Imobiliárias e corretores | D15: Nível 2 | E15: R$ 225 a 1.200 | F15: ~R$ 30/h | G15: segunda a quarta, das 9h às 11h | H15: o kit de entrega e as tags | I15: 2h35 de máquina · 60 g | J15: 10 contatos → 3 propostas → 1 pacote, em geral de corretor autônomo | K15: G-07 · Academias, boxes e escolas esportivas | L15: Fica na biblioteca: abra depois da primeira venda. | M15: 123 | N15: domingo, segunda ou terça
B16: G-09 | C16: G-09 · Papelarias e festa | D16: Nível 3 | E16: R$ 150 a 500 | F16: ~R$ 35/h | G16: terça ou quarta, das 10h às 11h30 | H16: o kit e o mostruário | I16: 2h05 de máquina · 33 g | J16: 10 abordagens → 2 a 3 interessadas → 1 lote-teste em até 2 semanas | K16: G-03 · Pet shops | L16: Máquina média e revenda: você vira o fornecedor 3D da papelaria, com tabela de atacado. Cada festa que ela fecha é um pedido seu. | M16: 23 | N16: segunda ou terça
B17: G-10 | C17: G-10 · Oficinas e pequena indústria | D17: Nível 3 · exige CAD | E17: R$ 80 a 1.500 | F17: R$ 50 a 200/h | G17: terça a quinta, das 14h às 16h | H17: o gabarito, os clips e a engrenagem | I17: 3h00 de máquina · 63 g | J17: 10 visitas → 3 peças medidas → 2 pedidos | K17: G-06 · Lojas de celular e assistências | L17: Você já modela peça com encaixe. Peça de reposição e gabarito pagam pelo valor da máquina parada, não pelo plástico. Nunca imprima peça de segurança. | M17: 234 | N17: segunda, terça ou quarta
B19: A coluna "Se precisar trocar"
B20: É o G-Code que o Painel sugere quando a decisão da semana 2 for TROCAR: duas levas completas, 20 visitas, sem nenhuma proposta na mão. É editável: escolha outro na lista se fizer mais sentido para você.
B22: Linha do G-Code escolhido (automático, não mexa): | F22: =IFERROR(MATCH(Painel!$E$7,$C$8:$C$17,0),0) -> 0
B23: G-Code indicado pelo Seletor (automático, não mexa): | F23: =IFERROR(INDEX($C$8:$C$17,MATCH(Seletor!$B$16,$B$8:$B$17,0)),"")
B24: Linha do G-Code do Seletor (automático, não mexa): | F24: =IFERROR(MATCH(Seletor!$B$16,$B$8:$B$17,0),0) -> 0
